README.md
setup.cfg
setup.py
CloudyDaze/MyAWS.py
CloudyDaze/MyEC2.py
CloudyDaze/MySCP.py
CloudyDaze/MySG.py
CloudyDaze/MySSH.py
CloudyDaze.egg-info/PKG-INFO
CloudyDaze.egg-info/SOURCES.txt
CloudyDaze.egg-info/dependency_links.txt
CloudyDaze.egg-info/requires.txt
CloudyDaze.egg-info/top_level.txt
bin/myEC2.py
bin/mySCP.py
bin/mySG.py
bin/mySSH.py