Metadata-Version: 2.1
Name: CloudyDaze
Version: 1.1
Summary: UNKNOWN
Home-page: https://github.com/eddo888/CloudyDaze
Author: David Edson
Author-email: eddo888@tpg.com.au
License: MIT
Download-URL: https://github.com/eddo888/CloudyDaze/archive/1.1.tar.gz
Platform: UNKNOWN
